basmati/__about__.py
basmati/__init__.py
basmati/py.typed
basmati-0.0.0.dist-info/METADATA
basmati-0.0.0.dist-info/WHEEL
basmati-0.0.0.dist-info/licenses/LICENSE.txt
basmati-0.0.0.dist-info/RECORD
